Metadata-Version: 1.1
Name: dictspec
Version: 0.2.1
Summary: validator for JSON/YAML/dict data
Home-page: http://github.org/olt/dictspec/
Author: Oliver Tonnhofer
Author-email: olt@omniscale.de
License: MIT License
Platform: UNKNOWN
Classifier: Development Status :: 4 - Beta
Classifier: License :: OSI Approved :: MIT License
Classifier: Operating System :: OS Independent
Classifier: Programming Language :: Python :: 2.5
Classifier: Programming Language :: Python :: 2.6
Classifier: Programming Language :: Python :: 2.7
